filternaut/__init__.py
filternaut/drf.py
filternaut/exceptions.py
filternaut/filters.py
filternaut/tree.py
filternaut/util.py
django_filternaut-1.0.1.dist-info/METADATA
django_filternaut-1.0.1.dist-info/WHEEL
django_filternaut-1.0.1.dist-info/top_level.txt
django_filternaut-1.0.1.dist-info/RECORD
