Metadata-Version: 2.1
Name: django-filternaut
Version: 1.0.1
Summary: Construct arbitrarily complex Django "Q" filters from flat data such as query parameters.
Home-page: https://github.com/bennullgraham/filternaut
Author: Ben Graham
Author-email: bgraham@bgraham.com.au
License: BSD
Classifier: Development Status :: 5 - Production/Stable
Classifier: Environment :: Web Environment
Classifier: Intended Audience :: Developers
Classifier: License :: OSI Approved :: BSD License
Classifier: Operating System :: OS Independent
Classifier: Programming Language :: Python
Classifier: Topic :: Utilities
Classifier: Framework :: Django
Requires-Dist: six >=1.9.0
Requires-Dist: django >=4.2
